smartphone_connector/__init__.py
smartphone_connector/colors.py
smartphone_connector/dictx.py
smartphone_connector/helpers.py
smartphone_connector/timings.py
smartphone_connector/types.py
smartphone_connector-0.0.115.dist-info/LICENSE
smartphone_connector-0.0.115.dist-info/METADATA
smartphone_connector-0.0.115.dist-info/WHEEL
smartphone_connector-0.0.115.dist-info/top_level.txt
smartphone_connector-0.0.115.dist-info/RECORD
