Metadata-Version: 2.1
Name: smartphone-connector
Version: 0.0.115
Summary: Talk to a socketio server
Home-page: https://github.com/lebalz/smartphone-connector
Author: Balthasar Hofer
Author-email: lebalz@outlook.com
License: UNKNOWN
Platform: UNKNOWN
Classifier: Programming Language :: Python :: 3
Classifier: License :: OSI Approved :: MIT License
Classifier: Operating System :: OS Independent
Requires-Python: >=3.8
Requires-Dist: python-socketio[client] (<5,>=4)
